openanalytics/__init__.py
openanalytics/checklibs.py
openanalytics/consumer.py
openanalytics/openanalytics.py
openanalytics/request.py
openanalytics/utils.py
openanalytics/version.py
openanalytics/connectors/ConnectorInterface.py
openanalytics/connectors/InfluxDBConnector.py
openanalytics/connectors/MongoDBConnector.py
openanalytics/connectors/SQLiteConnector.py
openanalytics/connectors/__init__.py
openanalytics/models/BaseModel.py
openanalytics/models/Identify.py
openanalytics/models/Log.py
openanalytics/models/Page.py
openanalytics/models/Token.py
openanalytics/models/Track.py
openanalytics/models/__init__.py
open_analytics-0.1.3.dist-info/LICENSE
open_analytics-0.1.3.dist-info/METADATA
open_analytics-0.1.3.dist-info/WHEEL
open_analytics-0.1.3.dist-info/top_level.txt
open_analytics-0.1.3.dist-info/RECORD
