Metadata-Version: 2.1
Name: open-analytics
Version: 0.1.3
Summary: Open sournce application analytics tracking library
Author-email: Lakitha Samarasinghe <Lakitharav@gmail.com>
License: Apache License v2.0
Project-URL: Homepage, https://github.com/LakithaRav/open-analytics
Keywords: analytics,tracking,tracing,logging
Requires-Python: >=3.8
License-File: LICENSE
Requires-Dist: pandas
Requires-Dist: setuptools
